pandoc_beamer_multigraphics/__init__.py
pandoc_beamer_multigraphics/_main.py
pandoc_beamer_multigraphics-1.2.0.0.dist-info/METADATA
pandoc_beamer_multigraphics-1.2.0.0.dist-info/WHEEL
pandoc_beamer_multigraphics-1.2.0.0.dist-info/entry_points.txt
pandoc_beamer_multigraphics-1.2.0.0.dist-info/licenses/LICENSE
pandoc_beamer_multigraphics-1.2.0.0.dist-info/RECORD
